{
  "_class": "symbolInstance",
  "booleanOperation": -1,
  "clippingMaskMode": 0,
  "do_objectID": "260A1200-75F7-4971-8182-F8952C6662DF",
  "exportOptions": {
    "_class": "exportOptions",
    "do_objectID": "D8255BE4-CDF3-4A6D-AF1E-D0C6D5CE28C2",
    "exportFormats": [
    ],
    "includedLayerIds": [
    ],
    "layerOptions": 0,
    "shouldTrim": false
  },
  "frame": {
    "_class": "rect",
    "constrainProportions": false,
    "do_objectID": "9BEB44F0-B4CE-4961-A228-112779F966F1",
    "height": 14,
    "width": 96,
    "x": 0,
    "y": 50
  },
  "hasClippingMask": false,
  "horizontalSpacing": 0,
  "isFixedToViewport": false,
  "isFlippedHorizontal": false,
  "isFlippedVertical": false,
  "isLocked": false,
  "isVisible": true,
  "layerListExpandedType": 0,
  "name": "text/machine-name",
  "nameIsFixed": false,
  "overrideValues": [
  ],
  "resizingConstraint": 47,
  "resizingType": 0,
  "rotation": 0,
  "scale": 1,
  "shouldBreakMaskChain": false,
  "style": {
    "_class": "style",
    "do_objectID": "359F70A4-FA52-457F-8A88-DF000C83AB02",
    "endMarkerType": 0,
    "miterLimit": 10,
    "startMarkerType": 0,
    "windingRule": 1
  },
  "symbolID": "8B5A0F79-FE15-4B4F-93AD-762881698CBB",
  "verticalSpacing": 0
}