{
  "_class": "artboard",
  "backgroundColor": {
    "_class": "color",
    "alpha": 1,
    "blue": 0.7754472373188406,
    "green": 0.7754472373188406,
    "red": 0.7754472373188406
  },
  "booleanOperation": -1,
  "clippingMaskMode": 0,
  "do_objectID": "FEFFFD87-0A65-45B2-94EE-98F163C1F6DB",
  "exportOptions": {
    "_class": "exportOptions",
    "do_objectID": "668D0BD7-F7D5-4D3F-8FB1-2EC415128CDD",
    "exportFormats": [
    ],
    "includedLayerIds": [
    ],
    "layerOptions": 0,
    "shouldTrim": false
  },
  "frame": {
    "_class": "rect",
    "constrainProportions": false,
    "do_objectID": "6309B6C6-DB44-4B7B-B3D8-FBC853E727BC",
    "height": 826,
    "width": 867,
    "x": 444,
    "y": -308
  },
  "groupLayout": {
    "_class": "MSImmutableFreeformGroupLayout",
    "do_objectID": "9D10AA78-F672-491B-9D76-9951B0F6B34F"
  },
  "hasBackgroundColor": false,
  "hasClickThrough": true,
  "hasClippingMask": false,
  "horizontalRulerData": {
    "_class": "rulerData",
    "base": 0,
    "do_objectID": "9DC3D36E-CDED-4024-842E-91D5C1A984D7",
    "guides": [
      1132,
      440
    ]
  },
  "includeBackgroundColorInExport": true,
  "includeInCloudUpload": true,
  "isFixedToViewport": false,
  "isFlippedHorizontal": false,
  "isFlippedVertical": false,
  "isFlowHome": false,
  "isLocked": false,
  "isVisible": true,
  "layerListExpandedType": 2,
  "layers": [
    {
      "class": "rectangle",
      "id": "9EFED7BF-20FB-4712-94F4-70FF682AA73F"
    },
    {
      "class": "group",
      "id": "781639DD-EE67-4798-B47B-C4D3E1E763FA"
    },
    {
      "class": "group",
      "id": "49F37E35-064D-4954-A488-42B57DF5C8BB"
    },
    {
      "class": "group",
      "id": "0628A925-0574-46D6-9556-4AA644DF7801"
    },
    {
      "class": "group",
      "id": "46D3A85F-9949-41FD-8B45-5058B122006B"
    },
    {
      "class": "group",
      "id": "33B27ACF-D6D2-4CB0-92A4-40841E779A84"
    }
  ],
  "name": "Text Styles",
  "nameIsFixed": true,
  "resizesContent": false,
  "resizingConstraint": 63,
  "resizingType": 0,
  "rotation": 0,
  "shouldBreakMaskChain": true,
  "style": {
    "_class": "style",
    "do_objectID": "0A36AA80-C1CA-41B1-AEF6-16B976063EA2",
    "endMarkerType": 0,
    "miterLimit": 10,
    "startMarkerType": 0,
    "windingRule": 1
  },
  "verticalRulerData": {
    "_class": "rulerData",
    "base": 0,
    "do_objectID": "539A3A56-C81D-4126-AB8E-99E5B4B90697",
    "guides": [
    ]
  }
}